netlas/__init__.py
netlas/__main__.py
netlas/client.py
netlas/exception.py
netlas/helpers.py
netlas-0.7.3.dist-info/licenses/LICENSE.md
netlas-0.7.3.dist-info/METADATA
netlas-0.7.3.dist-info/WHEEL
netlas-0.7.3.dist-info/entry_points.txt
netlas-0.7.3.dist-info/top_level.txt
netlas-0.7.3.dist-info/RECORD
