Metadata-Version: 2.4
Name: netlas
Version: 0.7.3
Summary: Netlas.io API package
Home-page: https://github.com/netlas-io/netlas-python
Author: Netlas Team
Author-email: support@netlas.io
Keywords: security,network
Classifier: Programming Language :: Python :: 3
Classifier: License :: OSI Approved :: MIT License
Classifier: Operating System :: OS Independent
Requires-Python: >=3.6
License-File: LICENSE.md
Requires-Dist: requests>=2.12.5
Requires-Dist: click>=7.0
Requires-Dist: PyYAML>=3.13
Requires-Dist: pygments>=2.5.0
Requires-Dist: tqdm>=4.0.0
Requires-Dist: appdirs>=1.4.3
Requires-Dist: rich>=13.7.1
Dynamic: author
Dynamic: author-email
Dynamic: classifier
Dynamic: description
Dynamic: description-content-type
Dynamic: home-page
Dynamic: keywords
Dynamic: license-file
Dynamic: requires-dist
Dynamic: requires-python
Dynamic: summary
